trainingnotifier/__init__.py
trainingnotifier/notifierCallback.py
trainingnotifier/build/lib/notifierCallback.py
tf_training_notifier-1.0.3.dist-info/LICENSE
tf_training_notifier-1.0.3.dist-info/METADATA
tf_training_notifier-1.0.3.dist-info/WHEEL
tf_training_notifier-1.0.3.dist-info/top_level.txt
tf_training_notifier-1.0.3.dist-info/RECORD
