Metadata-Version: 2.1
Name: tf-training-notifier
Version: 1.0.3
Summary: Sends telegram messages informing user about ML training job progress.
Author-email: Bart Gebka <bartg1259@gmail.com>
License: MIT License
Project-URL: Homepage, https://github.com/bart1259/tf-training-notifier
Keywords: tensorflow,machine learning,notifier,monitor,callback
Classifier: License :: OSI Approved :: MIT License
Classifier: Programming Language :: Python
Classifier: Programming Language :: Python :: 3
Requires-Python: >=3.8
License-File: LICENSE
Requires-Dist: pytimeparse
Requires-Dist: tensorflow (>=2.9)
Provides-Extra: dev
